[
    {
        "op": "replace",
        "path": "/story/group_1/5/nameAvCenter",
        "value": "まばゆ"
    },
    {
        "op": "replace",
        "path": "/story/group_1/5/textAvCenter",
        "value": "はぁ…"
    },
    {
        "op": "replace",
        "path": "/story/group_1/6/nameAvCenter",
        "value": "まばゆ"
    },
    {
        "op": "replace",
        "path": "/story/group_1/6/textAvCenter",
        "value": "あれから、時間停止の原因を@探ろうとしたものの…"
    },
    {
        "op": "replace",
        "path": "/story/group_1/7/nameAvCenter",
        "value": "まばゆ"
    },
    {
        "op": "replace",
        "path": "/story/group_1/7/textAvCenter",
        "value": "全然、わからない@ヒントさえ見つかんない"
    },
    {
        "op": "replace",
        "path": "/story/group_1/8/nameAvCenter",
        "value": "まばゆ"
    },
    {
        "op": "replace",
        "path": "/story/group_1/8/textAvCenter",
        "value": "時間停止のタイミングはバラバラ@強いていえば夕方から夜が多い？"
    },
    {
        "op": "replace",
        "path": "/story/group_1/9/nameAvCenter",
        "value": "まばゆ"
    },
    {
        "op": "replace",
        "path": "/story/group_1/9/textAvCenter",
        "value": "曜日ごとの傾向もないし@停止時間も長かったり短かったり"
    },
    {
        "op": "replace",
        "path": "/story/group_1/10/nameAvCenter",
        "value": "まばゆ"
    },
    {
        "op": "replace",
        "path": "/story/group_1/10/textAvCenter",
        "value": "テストの後、あの時みたいに@長い停止はまだなくて…"
    },
    {
        "op": "replace",
        "path": "/story/group_1/11/nameAvCenter",
        "value": "まばゆ"
    },
    {
        "op": "replace",
        "path": "/story/group_1/11/textAvCenter",
        "value": "止まった時間に閉じ込められずに@済んだのは、良かったですけど"
    },
    {
        "op": "replace",
        "path": "/story/group_1/12/nameAvCenter",
        "value": "まばゆ"
    },
    {
        "op": "replace",
        "path": "/story/group_1/12/textAvCenter",
        "value": "自然現象か、人為的なものか@それすらもわかんなくて…"
    },
    {
        "op": "replace",
        "path": "/story/group_1/13/nameAvCenter",
        "value": "まばゆ"
    },
    {
        "op": "replace",
        "path": "/story/group_1/13/textAvCenter",
        "value": "結局、時間が止まって@良かったことといえば…"
    },
    {
        "op": "replace",
        "path": "/story/group_1/14/nameAvCenter",
        "value": "まばゆ"
    },
    {
        "op": "replace",
        "path": "/story/group_1/14/textAvCenter",
        "value": "ラテアートが上達した@ことくらい…トホホホ…"
    },
    {
        "op": "replace",
        "path": "/story/group_1/19/FnarrationFontSize",
        "value": 23
    },
    {
        "op": "replace",
        "path": "/story/group_1/19/nameFnarration",
        "value": "まばゆ"
    },
    {
        "op": "replace",
        "path": "/story/group_1/19/progressFnarration",
        "value": "(あ、時間が進んだ…)"
    },
    {
        "op": "replace",
        "path": "/story/group_1/21/nameAvRight",
        "value": "咲笑"
    },
    {
        "op": "replace",
        "path": "/story/group_1/21/textAvRight",
        "value": "あら、まばゆちゃん@また練習してるの？"
    },
    {
        "op": "replace",
        "path": "/story/group_1/23/nameAvRight",
        "value": "咲笑"
    },
    {
        "op": "replace",
        "path": "/story/group_1/23/textAvRight",
        "value": "まあ、かわいいキリンさん！"
    },
    {
        "op": "replace",
        "path": "/story/group_1/24/nameAvLeft",
        "value": "まばゆ"
    },
    {
        "op": "replace",
        "path": "/story/group_1/24/textAvLeft",
        "value": "へ…ヘビ、です…"
    },
    {
        "op": "replace",
        "path": "/story/group_1/25/nameAvRight",
        "value": "咲笑"
    },
    {
        "op": "replace",
        "path": "/story/group_1/25/textAvRight",
        "value": "あ、あらぁ…？@うふふふふ…"
    },
    {
        "op": "replace",
        "path": "/story/group_1/27/FnarrationFontSize",
        "value": 23
    },
    {
        "op": "replace",
        "path": "/story/group_1/27/nameFnarration",
        "value": "まばゆ"
    },
    {
        "op": "replace",
        "path": "/story/group_1/27/progressFnarration",
        "value": "(上達…@してるつもりなんだけどなあ)"
    },
    {
        "op": "replace",
        "path": "/story/group_1/31/nameAvLeft",
        "value": "まばゆ"
    },
    {
        "op": "replace",
        "path": "/story/group_1/31/textAvLeft",
        "value": "はぁ…また、止まった"
    },
    {
        "op": "replace",
        "path": "/story/group_1/32/nameAvLeft",
        "value": "まばゆ"
    },
    {
        "op": "replace",
        "path": "/story/group_1/32/textAvLeft",
        "value": "やれやれ@これはもう１杯、練習しろってこと…"
    },
    {
        "op": "replace",
        "path": "/story/group_1/34/nameAvCenter",
        "value": "まばゆ"
    },
    {
        "op": "replace",
        "path": "/story/group_1/34/textAvCenter",
        "value": "え…"
    },
    {
        "op": "replace",
        "path": "/story/group_1/37/nameAvRight",
        "value": "？？？"
    },
    {
        "op": "replace",
        "path": "/story/group_1/37/textAvRight",
        "value": "あっちです！あの、工場！"
    },
    {
        "op": "replace",
        "path": "/story/group_1/38/nameAvRight",
        "value": "？？？"
    },
    {
        "op": "replace",
        "path": "/story/group_1/38/textAvRight",
        "value": "ええ、先にいくわね！"
    },
    {
        "op": "replace",
        "path": "/story/group_1/42/FnarrationFontSize",
        "value": 23
    },
    {
        "op": "replace",
        "path": "/story/group_1/42/nameFnarration",
        "value": "まばゆ"
    },
    {
        "op": "replace",
        "path": "/story/group_1/42/progressFnarration",
        "value": "(あ…あれ？)"
    },
    {
        "op": "replace",
        "path": "/story/group_1/43/progressFnarration",
        "value": "(今、店の前を通ったのって…)"
    },
    {
        "op": "replace",
        "path": "/story/group_1/45/nameAvCenter",
        "value": "まばゆ"
    },
    {
        "op": "replace",
        "path": "/story/group_1/45/textAvCenter",
        "value": "っ!!"
    },
    {
        "op": "replace",
        "path": "/story/group_1/49/FnarrationFontSize",
        "value": 23
    },
    {
        "op": "replace",
        "path": "/story/group_1/49/nameFnarration",
        "value": "まばゆ"
    },
    {
        "op": "replace",
        "path": "/story/group_1/49/progressFnarration",
        "value": "(人影――走ってる！)"
    },
    {
        "op": "replace",
        "path": "/story/group_1/50/progressFnarration",
        "value": "(私の他にも、止まってる時間の@中で動ける人が、ふたり！)"
    },
    {
        "op": "replace",
        "path": "/story/group_1/51/progressFnarration",
        "value": "(私の他にも、いるんだ！)"
    },
    {
        "op": "replace",
        "path": "/story/group_1/52/progressFnarration",
        "value": "(追いかけなきゃ!!)"
    }
]