[
    {
        "op": "replace",
        "path": "/story/group_1/2/FnarrationFontSize",
        "value": 23
    },
    {
        "op": "replace",
        "path": "/story/group_1/2/nameFnarration",
        "value": "まばゆ"
    },
    {
        "op": "replace",
        "path": "/story/group_1/2/progressFnarration",
        "value": "(ここ…間違いない)"
    },
    {
        "op": "replace",
        "path": "/story/group_1/3/progressFnarration",
        "value": "(魔女の結界)"
    },
    {
        "op": "replace",
        "path": "/story/group_1/7/nameAvCenter",
        "value": "まどか"
    },
    {
        "op": "replace",
        "path": "/story/group_1/7/textAvCenter",
        "value": "…………"
    },
    {
        "op": "replace",
        "path": "/story/group_1/11/FnarrationFontSize",
        "value": 23
    },
    {
        "op": "replace",
        "path": "/story/group_1/11/nameFnarration",
        "value": "まばゆ"
    },
    {
        "op": "replace",
        "path": "/story/group_1/11/progressFnarration",
        "value": "(あそこにいるのって@鹿目まどかさん…？)"
    },
    {
        "op": "replace",
        "path": "/story/group_1/12/progressFnarration",
        "value": "(牛の形をした…魔女？と@向かい合って…)"
    },
    {
        "op": "replace",
        "path": "/story/group_1/13/progressFnarration",
        "value": "(でも、どっちも動いてない)"
    },
    {
        "op": "replace",
        "path": "/story/group_1/14/progressFnarration",
        "value": "(時間が止まってる@つまり…)"
    },
    {
        "op": "replace",
        "path": "/story/group_1/15/progressFnarration",
        "value": "(時間停止の魔法を使うのは@鹿目さんじゃない)"
    },
    {
        "op": "replace",
        "path": "/story/group_1/16/progressFnarration",
        "value": "(となると、他に…)"
    },
    {
        "op": "replace",
        "path": "/story/group_1/19/nameAvLeft",
        "value": "ほむら"
    },
    {
        "op": "replace",
        "path": "/story/group_1/19/textAvLeft",
        "value": "…………"
    },
    {
        "op": "replace",
        "path": "/story/group_1/21/FnarrationFontSize",
        "value": 23
    },
    {
        "op": "replace",
        "path": "/story/group_1/21/nameFnarration",
        "value": "まばゆ"
    },
    {
        "op": "replace",
        "path": "/story/group_1/21/progressFnarration",
        "value": "(!!)"
    },
    {
        "op": "replace",
        "path": "/story/group_1/22/progressFnarration",
        "value": "(暁美ほむらさん！)"
    },
    {
        "op": "replace",
        "path": "/story/group_1/23/progressFnarration",
        "value": "(魔法少女の姿で…@動けるの？)"
    },
    {
        "op": "replace",
        "path": "/story/group_1/24/progressFnarration",
        "value": "(時間停止の魔法を使えるのは@暁美さん？)"
    },
    {
        "op": "replace",
        "path": "/story/group_1/25/progressFnarration",
        "value": "(でも、なにか思い詰めてる@みたいに見えるけど…)"
    },
    {
        "op": "replace",
        "path": "/story/group_1/27/nameAvLeft",
        "value": "ほむら"
    },
    {
        "op": "replace",
        "path": "/story/group_1/27/textAvLeft",
        "value": "鹿目さん…お願い"
    },
    {
        "op": "replace",
        "path": "/story/group_1/28/nameAvLeft",
        "value": "ほむら"
    },
    {
        "op": "replace",
        "path": "/story/group_1/28/textAvLeft",
        "value": "私の話を、聞いて"
    },
    {
        "op": "replace",
        "path": "/story/group_1/31/nameAvRight",
        "value": "まどか"
    },
    {
        "op": "replace",
        "path": "/story/group_1/31/textAvRight",
        "value": "こうなったら、わたしひとりで@戦うしか…！"
    },
    {
        "op": "replace",
        "path": "/story/group_1/32/nameAvRight",
        "value": "まどか"
    },
    {
        "op": "replace",
        "path": "/story/group_1/32/textAvRight",
        "value": "って、え？あれ？@なんか、動きが止まって…"
    },
    {
        "op": "replace",
        "path": "/story/group_1/33/nameAvLeft",
        "value": "ほむら"
    },
    {
        "op": "replace",
        "path": "/story/group_1/33/textAvLeft",
        "value": "鹿目さん"
    },
    {
        "op": "replace",
        "path": "/story/group_1/34/nameAvRight",
        "value": "まどか"
    },
    {
        "op": "replace",
        "path": "/story/group_1/34/textAvRight",
        "value": "えっ？わっ、こ、この間の…"
    },
    {
        "op": "replace",
        "path": "/story/group_1/35/nameAvRight",
        "value": "まどか"
    },
    {
        "op": "replace",
        "path": "/story/group_1/35/textAvRight",
        "value": "暁美、さん？"
    },
    {
        "op": "replace",
        "path": "/story/group_1/36/nameAvLeft",
        "value": "ほむら"
    },
    {
        "op": "replace",
        "path": "/story/group_1/36/textAvLeft",
        "value": "離れないで"
    },
    {
        "op": "replace",
        "path": "/story/group_1/37/nameAvLeft",
        "value": "ほむら"
    },
    {
        "op": "replace",
        "path": "/story/group_1/37/textAvLeft",
        "value": "私の魔法で時間を止めてるの@だから、心配しなくて大丈夫"
    },
    {
        "op": "replace",
        "path": "/story/group_1/38/nameAvRight",
        "value": "まどか"
    },
    {
        "op": "replace",
        "path": "/story/group_1/38/textAvRight",
        "value": "え…そ、そうなんだ！@すごいね、暁美さん"
    },
    {
        "op": "replace",
        "path": "/story/group_1/40/nameAvRight",
        "value": "まどか"
    },
    {
        "op": "replace",
        "path": "/story/group_1/40/textAvRight",
        "value": "だったら…うん、お願い！"
    },
    {
        "op": "replace",
        "path": "/story/group_1/41/nameAvRight",
        "value": "まどか"
    },
    {
        "op": "replace",
        "path": "/story/group_1/41/textAvRight",
        "value": "わたしと一緒に@魔女を倒す手伝いを…"
    },
    {
        "op": "replace",
        "path": "/story/group_1/42/nameAvLeft",
        "value": "ほむら"
    },
    {
        "op": "replace",
        "path": "/story/group_1/42/textAvLeft",
        "value": "鹿目さん、聞いて！"
    },
    {
        "op": "replace",
        "path": "/story/group_1/43/nameAvRight",
        "value": "まどか"
    },
    {
        "op": "replace",
        "path": "/story/group_1/43/textAvRight",
        "value": "え…暁美さん？"
    },
    {
        "op": "replace",
        "path": "/story/group_1/44/nameAvLeft",
        "value": "ほむら"
    },
    {
        "op": "replace",
        "path": "/story/group_1/44/textAvLeft",
        "value": "今はこうやって、時間を@止めているけれども…"
    },
    {
        "op": "replace",
        "path": "/story/group_1/45/nameAvLeft",
        "value": "ほむら"
    },
    {
        "op": "replace",
        "path": "/story/group_1/45/textAvLeft",
        "value": "私の力は、それだけじゃないの"
    },
    {
        "op": "replace",
        "path": "/story/group_1/46/nameAvRight",
        "value": "まどか"
    },
    {
        "op": "replace",
        "path": "/story/group_1/46/textAvRight",
        "value": "それは…どういう意味？"
    },
    {
        "op": "replace",
        "path": "/story/group_1/47/nameAvLeft",
        "value": "ほむら"
    },
    {
        "op": "replace",
        "path": "/story/group_1/47/textAvLeft",
        "value": "今から１ヶ月も経たないうちに@ワルプルギスの夜がやってくる"
    },
    {
        "op": "replace",
        "path": "/story/group_1/48/nameAvLeft",
        "value": "ほむら"
    },
    {
        "op": "replace",
        "path": "/story/group_1/48/textAvLeft",
        "value": "私たちは皆、歯が立たなくて@見滝原がめちゃくちゃになる"
    },
    {
        "op": "replace",
        "path": "/story/group_1/49/nameAvLeft",
        "value": "ほむら"
    },
    {
        "op": "replace",
        "path": "/story/group_1/49/textAvLeft",
        "value": "私は、その未来から@この世界に戻ってきたの"
    },
    {
        "op": "replace",
        "path": "/story/group_1/50/nameAvLeft",
        "value": "ほむら"
    },
    {
        "op": "replace",
        "path": "/story/group_1/50/textAvLeft",
        "value": "鹿目さんを、助けるために"
    },
    {
        "op": "replace",
        "path": "/story/group_1/51/nameAvRight",
        "value": "まどか"
    },
    {
        "op": "replace",
        "path": "/story/group_1/51/textAvRight",
        "value": "わたしを…助けるために？"
    },
    {
        "op": "replace",
        "path": "/story/group_1/52/nameAvLeft",
        "value": "ほむら"
    },
    {
        "op": "replace",
        "path": "/story/group_1/52/textAvLeft",
        "value": "ごめんなさい"
    },
    {
        "op": "replace",
        "path": "/story/group_1/53/nameAvLeft",
        "value": "ほむら"
    },
    {
        "op": "replace",
        "path": "/story/group_1/53/textAvLeft",
        "value": "急にこんなことを言っても@信じられないよね"
    },
    {
        "op": "replace",
        "path": "/story/group_1/54/nameAvRight",
        "value": "まどか"
    },
    {
        "op": "replace",
        "path": "/story/group_1/54/textAvRight",
        "value": "暁美さん…あ、あの、わたしね@信じられないっていうよりも…"
    },
    {
        "op": "replace",
        "path": "/story/group_1/55/nameAvRight",
        "value": "まどか"
    },
    {
        "op": "replace",
        "path": "/story/group_1/55/textAvRight",
        "value": "ビックリしちゃって@話に追いつけないっていうか…"
    },
    {
        "op": "replace",
        "path": "/story/group_1/56/nameAvLeft",
        "value": "ほむら"
    },
    {
        "op": "replace",
        "path": "/story/group_1/56/textAvLeft",
        "value": "鹿目さん！"
    },
    {
        "op": "replace",
        "path": "/story/group_1/57/nameAvLeft",
        "value": "ほむら"
    },
    {
        "op": "replace",
        "path": "/story/group_1/57/textAvLeft",
        "value": "私、怖かったの"
    },
    {
        "op": "replace",
        "path": "/story/group_1/58/nameAvRight",
        "value": "まどか"
    },
    {
        "op": "replace",
        "path": "/story/group_1/58/textAvRight",
        "value": "怖かった…？"
    },
    {
        "op": "replace",
        "path": "/story/group_1/59/nameAvLeft",
        "value": "ほむら"
    },
    {
        "op": "replace",
        "path": "/story/group_1/59/textAvLeft",
        "value": "本当の事を話しても、鹿目さんが@信じてくれなかったらどうしよう"
    },
    {
        "op": "replace",
        "path": "/story/group_1/60/nameAvLeft",
        "value": "ほむら"
    },
    {
        "op": "replace",
        "path": "/story/group_1/60/textAvLeft",
        "value": "私よりもキュゥべえを信じたら@どうしようって"
    },
    {
        "op": "replace",
        "path": "/story/group_1/61/nameAvLeft",
        "value": "ほむら"
    },
    {
        "op": "replace",
        "path": "/story/group_1/61/textAvLeft",
        "value": "だから…怖くて、巴さんの前から@逃げちゃって…"
    },
    {
        "op": "replace",
        "path": "/story/group_1/62/nameAvRight",
        "value": "まどか"
    },
    {
        "op": "replace",
        "path": "/story/group_1/62/textAvRight",
        "value": "それって…この前の@マミさんの家の…？"
    },
    {
        "op": "replace",
        "path": "/story/group_1/63/nameAvLeft",
        "value": "ほむら"
    },
    {
        "op": "replace",
        "path": "/story/group_1/63/textAvLeft",
        "value": "でも、もう一回、考えて@考え直して、ここに来たの"
    },
    {
        "op": "replace",
        "path": "/story/group_1/64/nameAvLeft",
        "value": "ほむら"
    },
    {
        "op": "replace",
        "path": "/story/group_1/64/textAvLeft",
        "value": "あなたと過ごした時の中で@私は勇気をもらった"
    },
    {
        "op": "replace",
        "path": "/story/group_1/65/nameAvLeft",
        "value": "ほむら"
    },
    {
        "op": "replace",
        "path": "/story/group_1/65/textAvLeft",
        "value": "弱虫で、何もできなかった私でも@今は、皆の役に立てるって"
    },
    {
        "op": "replace",
        "path": "/story/group_1/66/nameAvLeft",
        "value": "ほむら"
    },
    {
        "op": "replace",
        "path": "/story/group_1/66/textAvLeft",
        "value": "魔法少女の力を使って@誰かを守ることができるって"
    },
    {
        "op": "replace",
        "path": "/story/group_1/67/nameAvLeft",
        "value": "ほむら"
    },
    {
        "op": "replace",
        "path": "/story/group_1/67/textAvLeft",
        "value": "そんな私になれたのは、あなたが@私を信じてくれたおかげだから"
    },
    {
        "op": "replace",
        "path": "/story/group_1/68/nameAvLeft",
        "value": "ほむら"
    },
    {
        "op": "replace",
        "path": "/story/group_1/68/textAvLeft",
        "value": "だから私も、鹿目さんを@信じようって…"
    },
    {
        "op": "replace",
        "path": "/story/group_1/70/nameAvLeft",
        "value": "ほむら"
    },
    {
        "op": "replace",
        "path": "/story/group_1/70/textAvLeft",
        "value": "そう決めて、ここに来たの！"
    },
    {
        "op": "replace",
        "path": "/story/group_1/71/nameAvRight",
        "value": "まどか"
    },
    {
        "op": "replace",
        "path": "/story/group_1/71/textAvRight",
        "value": "暁美さん…"
    },
    {
        "op": "replace",
        "path": "/story/group_1/72/nameAvLeft",
        "value": "ほむら"
    },
    {
        "op": "replace",
        "path": "/story/group_1/72/textAvLeft",
        "value": "あ…ご、ごめんなさい"
    },
    {
        "op": "replace",
        "path": "/story/group_1/73/nameAvLeft",
        "value": "ほむら"
    },
    {
        "op": "replace",
        "path": "/story/group_1/73/textAvLeft",
        "value": "急に、一方的に…"
    },
    {
        "op": "replace",
        "path": "/story/group_1/74/nameAvRight",
        "value": "まどか"
    },
    {
        "op": "replace",
        "path": "/story/group_1/74/textAvRight",
        "value": "ううん、あなたの気持ち@よくわかったよ"
    },
    {
        "op": "replace",
        "path": "/story/group_1/75/nameAvLeft",
        "value": "ほむら"
    },
    {
        "op": "replace",
        "path": "/story/group_1/75/textAvLeft",
        "value": "本当に…!?"
    },
    {
        "op": "replace",
        "path": "/story/group_1/76/nameAvRight",
        "value": "まどか"
    },
    {
        "op": "replace",
        "path": "/story/group_1/76/textAvRight",
        "value": "まだ色々聞きたいことは@あるけれど…"
    },
    {
        "op": "replace",
        "path": "/story/group_1/77/nameAvRight",
        "value": "まどか"
    },
    {
        "op": "replace",
        "path": "/story/group_1/77/textAvRight",
        "value": "わたしは暁美さんを…@ほむらちゃんを、信じるよ！"
    },
    {
        "op": "replace",
        "path": "/story/group_1/79/nameAvLeft",
        "value": "ほむら"
    },
    {
        "op": "replace",
        "path": "/story/group_1/79/textAvLeft",
        "value": "…うん"
    },
    {
        "op": "replace",
        "path": "/story/group_1/80/nameAvLeft",
        "value": "ほむら"
    },
    {
        "op": "replace",
        "path": "/story/group_1/80/textAvLeft",
        "value": "ありがとう、鹿目さん！"
    },
    {
        "op": "replace",
        "path": "/story/group_1/81/nameAvRight",
        "value": "まどか"
    },
    {
        "op": "replace",
        "path": "/story/group_1/81/textAvRight",
        "value": "さあ、それじゃあ時間停止を@解いて…"
    },
    {
        "op": "replace",
        "path": "/story/group_1/82/nameAvLeft",
        "value": "ほむら"
    },
    {
        "op": "replace",
        "path": "/story/group_1/82/textAvLeft",
        "value": "鹿目さん、あなたは弓矢を放つ@魔法を使えるよね？"
    },
    {
        "op": "replace",
        "path": "/story/group_1/83/nameAvRight",
        "value": "まどか"
    },
    {
        "op": "replace",
        "path": "/story/group_1/83/textAvRight",
        "value": "あ…うん"
    },
    {
        "op": "replace",
        "path": "/story/group_1/84/nameAvLeft",
        "value": "ほむら"
    },
    {
        "op": "replace",
        "path": "/story/group_1/84/textAvLeft",
        "value": "停止した時間の中で私たちが@触れたものは動いてしまう"
    },
    {
        "op": "replace",
        "path": "/story/group_1/85/nameAvLeft",
        "value": "ほむら"
    },
    {
        "op": "replace",
        "path": "/story/group_1/85/textAvLeft",
        "value": "だから、魔女に直接触れたら@時間停止をする意味がないわ"
    },
    {
        "op": "replace",
        "path": "/story/group_1/86/nameAvRight",
        "value": "まどか"
    },
    {
        "op": "replace",
        "path": "/story/group_1/86/textAvRight",
        "value": "そうなんだ"
    },
    {
        "op": "replace",
        "path": "/story/group_1/87/nameAvLeft",
        "value": "ほむら"
    },
    {
        "op": "replace",
        "path": "/story/group_1/87/textAvLeft",
        "value": "その代わり、何もつがえずに@弓を鳴らしてみて"
    },
    {
        "op": "replace",
        "path": "/story/group_1/88/nameAvRight",
        "value": "まどか"
    },
    {
        "op": "replace",
        "path": "/story/group_1/88/textAvRight",
        "value": "何も、つがえないで…？"
    },
    {
        "op": "replace",
        "path": "/story/group_1/89/nameAvLeft",
        "value": "ほむら"
    },
    {
        "op": "replace",
        "path": "/story/group_1/89/textAvLeft",
        "value": "そう、鳴弦っていって@悪霊を祓うおまじないみたいに"
    },
    {
        "op": "replace",
        "path": "/story/group_1/90/nameAvRight",
        "value": "まどか"
    },
    {
        "op": "replace",
        "path": "/story/group_1/90/textAvRight",
        "value": "こ、こうかな…？"
    },
    {
        "op": "replace",
        "path": "/story/group_1/92/nameAvRight",
        "value": "まどか"
    },
    {
        "op": "replace",
        "path": "/story/group_1/92/textAvRight",
        "value": "わっ！く、空気が吸い込まれて…"
    },
    {
        "op": "replace",
        "path": "/story/group_1/93/nameAvRight",
        "value": "まどか"
    },
    {
        "op": "replace",
        "path": "/story/group_1/93/textAvRight",
        "value": "あれ？でも、途中で止まった？"
    },
    {
        "op": "replace",
        "path": "/story/group_1/94/nameAvLeft",
        "value": "ほむら"
    },
    {
        "op": "replace",
        "path": "/story/group_1/94/textAvLeft",
        "value": "魔法で干渉はできないけど@物理的な力は利用できるから"
    },
    {
        "op": "replace",
        "path": "/story/group_1/95/nameAvLeft",
        "value": "ほむら"
    },
    {
        "op": "replace",
        "path": "/story/group_1/95/textAvLeft",
        "value": "次は別の角度から@同じことを繰り返して"
    },
    {
        "op": "replace",
        "path": "/story/group_1/96/nameAvRight",
        "value": "まどか"
    },
    {
        "op": "replace",
        "path": "/story/group_1/96/textAvRight",
        "value": "うん、わかった"
    },
    {
        "op": "replace",
        "path": "/story/group_1/97/nameAvRight",
        "value": "まどか"
    },
    {
        "op": "replace",
        "path": "/story/group_1/97/textAvRight",
        "value": "[flashEffect:flashWhite2][surround:8062_string]こんな、感じかな…？"
    },
    {
        "op": "replace",
        "path": "/story/group_1/99/nameAvLeft",
        "value": "ほむら"
    },
    {
        "op": "replace",
        "path": "/story/group_1/99/textAvLeft",
        "value": "良い調子"
    },
    {
        "op": "replace",
        "path": "/story/group_1/100/nameAvLeft",
        "value": "ほむら"
    },
    {
        "op": "replace",
        "path": "/story/group_1/100/textAvLeft",
        "value": "それじゃあそろそろ…"
    },
    {
        "op": "replace",
        "path": "/story/group_1/116/nameAvRight",
        "value": "まどか"
    },
    {
        "op": "replace",
        "path": "/story/group_1/116/textAvRight",
        "value": "あ…う、うそ"
    },
    {
        "op": "replace",
        "path": "/story/group_1/117/nameAvRight",
        "value": "まどか"
    },
    {
        "op": "replace",
        "path": "/story/group_1/117/textAvRight",
        "value": "簡単に、倒せちゃった…"
    },
    {
        "op": "replace",
        "path": "/story/group_1/118/nameAvLeft",
        "value": "ほむら"
    },
    {
        "op": "replace",
        "path": "/story/group_1/118/textAvLeft",
        "value": "波が大きく重なって@威力がグンと増すの"
    },
    {
        "op": "replace",
        "path": "/story/group_1/119/nameAvLeft",
        "value": "ほむら"
    },
    {
        "op": "replace",
        "path": "/story/group_1/119/textAvLeft",
        "value": "私たちが、前の周の特訓で@見つけた必殺技だよ"
    },
    {
        "op": "replace",
        "path": "/story/group_1/120/nameAvRight",
        "value": "まどか"
    },
    {
        "op": "replace",
        "path": "/story/group_1/120/textAvRight",
        "value": "必殺技…"
    },
    {
        "op": "replace",
        "path": "/story/group_1/121/nameAvRight",
        "value": "まどか"
    },
    {
        "op": "replace",
        "path": "/story/group_1/121/textAvRight",
        "value": "すごいよ、ほむらちゃん！"
    },
    {
        "op": "replace",
        "path": "/story/group_1/122/nameAvLeft",
        "value": "ほむら"
    },
    {
        "op": "replace",
        "path": "/story/group_1/122/textAvLeft",
        "value": "…うん"
    },
    {
        "op": "replace",
        "path": "/story/group_1/123/nameAvLeft",
        "value": "ほむら"
    },
    {
        "op": "replace",
        "path": "/story/group_1/123/textAvLeft",
        "value": "今度は一緒に@ワルプルギスの夜を倒そう"
    },
    {
        "op": "replace",
        "path": "/story/group_1/126/FnarrationFontSize",
        "value": 23
    },
    {
        "op": "replace",
        "path": "/story/group_1/126/nameFnarration",
        "value": "まばゆ"
    },
    {
        "op": "replace",
        "path": "/story/group_1/126/progressFnarration",
        "value": "(な…なんという…!!)"
    },
    {
        "op": "replace",
        "path": "/story/group_1/127/progressFnarration",
        "value": "(色々な新事実が@一気に発覚してしまいました)"
    },
    {
        "op": "replace",
        "path": "/story/group_1/128/progressFnarration",
        "value": "(これは一度家に帰って@情報を整理しなければ…)"
    }
]