[
    {
        "op": "remove",
        "path": "/story/group_1/0/bgm"
    },
    {
        "op": "remove",
        "path": "/story/group_1/0/nameLeft"
    },
    {
        "op": "remove",
        "path": "/story/group_1/0/textLeft"
    },
    {
        "op": "add",
        "path": "/story/group_1/0/autoTurnLast",
        "value": 0.2
    },
    {
        "op": "add",
        "path": "/story/group_1/0/turnChangeIn",
        "value": "fadeIn"
    },
    {
        "op": "replace",
        "path": "/story/group_1/0/chara/0/motion",
        "value": 0
    },
    {
        "op": "add",
        "path": "/story/group_1/1",
        "value": {
            "bgm": "bgm01_anime03",
            "chara": [
                {
                    "id": 300902,
                    "motion": 200
                }
            ],
            "nameLeft": "#BELLA=nameLeft=SPINA#",
            "textLeft": "#BELLA=textLeft=SPINA#",
            "turnChangeOut": "fadeOut"
        }
    },
    {
        "op": "add",
        "path": "/story/group_1/10/textClear",
        "value": 1
    },
    {
        "op": "remove",
        "path": "/story/group_1/25/nameLeft"
    },
    {
        "op": "remove",
        "path": "/story/group_1/25/textLeft"
    },
    {
        "op": "remove",
        "path": "/story/group_1/25/turnChangeOut"
    },
    {
        "op": "add",
        "path": "/story/group_1/25/autoTurnLast",
        "value": 1
    },
    {
        "op": "replace",
        "path": "/story/group_1/25/bgm",
        "value": "stop"
    },
    {
        "op": "add",
        "path": "/story/group_1/26",
        "value": {
            "bgm": "bgm01_anime07",
            "chara": [
                {
                    "id": 300902
                }
            ],
            "nameLeft": "#BELLA=nameLeft=SPINA#",
            "textLeft": "#BELLA=textLeft=SPINA#",
            "turnChangeOut": "fadeOut"
        }
    },
    {
        "op": "remove",
        "path": "/story/group_1/33/chara"
    },
    {
        "op": "remove",
        "path": "/story/group_1/33/nameCenter"
    },
    {
        "op": "remove",
        "path": "/story/group_1/33/textCenter"
    },
    {
        "op": "remove",
        "path": "/story/group_1/33/turnChangeOut"
    },
    {
        "op": "add",
        "path": "/story/group_1/33/autoTurnLast",
        "value": 0.1
    },
    {
        "op": "replace",
        "path": "/story/group_1/33/bg",
        "value": "bg_adv_19231.jpg"
    },
    {
        "op": "replace",
        "path": "/story/group_1/33/bgm",
        "value": "stop"
    },
    {
        "op": "add",
        "path": "/story/group_1/34",
        "value": {
            "bgm": "bgm03_story09",
            "chara": [
                {
                    "cheek": 0,
                    "face": "mtn_ex_010.exp.json",
                    "id": 300902,
                    "lipSynch": 0,
                    "motion": 1,
                    "pos": 1,
                    "soulGem": 0
                }
            ],
            "nameCenter": "#BELLA=nameCenter=SPINA#",
            "textCenter": "#BELLA=textCenter=SPINA#",
            "turnChangeOut": "rollOut"
        }
    },
    {
        "op": "add",
        "path": "/story/group_1/42/bg",
        "value": "bg_adv_21073.jpg"
    },
    {
        "op": "replace",
        "path": "/version",
        "value": 3
    }
]