[
    {
        "op": "add",
        "path": "/story/group_1/10/item",
        "value": [
            {
                "path": "resource/scenario/img/51126_tower_Ashley/51126_kumanosuke.png",
                "posX": 300,
                "posY": 0,
                "visible": "appear"
            }
        ]
    },
    {
        "op": "add",
        "path": "/story/group_1/10/chara/0/pos",
        "value": 0
    },
    {
        "op": "remove",
        "path": "/story/group_1/11/textCenter"
    },
    {
        "op": "add",
        "path": "/story/group_1/11/textLeft",
        "value": "#BELLA=textLeft=SPINA#"
    },
    {
        "op": "remove",
        "path": "/story/group_1/12/textCenter"
    },
    {
        "op": "add",
        "path": "/story/group_1/12/textLeft",
        "value": "#BELLA=textLeft=SPINA#"
    },
    {
        "op": "remove",
        "path": "/story/group_1/13/textCenter"
    },
    {
        "op": "add",
        "path": "/story/group_1/13/textLeft",
        "value": "#BELLA=textLeft=SPINA#"
    }
]